nseparser/__init__.py
nseparser/company_info.py
nseparser/config.py
nseparser/eod_prices.py
nseparser/testing.py
nseparser/config/config_sample.yaml
nseparser-0.1.2.dist-info/METADATA
nseparser-0.1.2.dist-info/WHEEL
nseparser-0.1.2.dist-info/top_level.txt
nseparser-0.1.2.dist-info/RECORD
