Metadata-Version: 2.4
Name: nseparser
Version: 0.1.2
Summary: A package for parsing nse website
Author-email: Unknown <unknown@example.com>
License-Expression: MIT
Requires-Dist: chameli
Requires-Dist: ohlcutils
